LICENSE.md
MANIFEST.in
README.md
setup.cfg
setup.py
requirements/base.in
requirements/dev.in
src/buildbot_docker_swarm_worker/__init__.py
src/buildbot_docker_swarm_worker/_plugin.py
src/buildbot_docker_swarm_worker.egg-info/PKG-INFO
src/buildbot_docker_swarm_worker.egg-info/SOURCES.txt
src/buildbot_docker_swarm_worker.egg-info/dependency_links.txt
src/buildbot_docker_swarm_worker.egg-info/entry_points.txt
src/buildbot_docker_swarm_worker.egg-info/requires.txt
src/buildbot_docker_swarm_worker.egg-info/top_level.txt