Metadata-Version: 2.1
Name: buildbot-docker-swarm-worker
Version: 0.1.3
Summary: Buildbot worker for Docker Swarm
Home-page: https://github.com/cjolowicz/buildbot-docker-swarm-worker
Author: Claudio Jolowicz
Author-email: mail@claudiojolowicz.com
Maintainer: Claudio Jolowicz
Maintainer-email: mail@claudiojolowicz.com
License: MIT
Keywords: buildbot,docker,swarm
Platform: UNKNOWN
Classifier: Development Status :: 3 - Alpha
Classifier: License :: OSI Approved :: MIT License
Classifier: Operating System :: OS Independent
Classifier: Programming Language :: Python
Classifier: Programming Language :: Python :: 3
Classifier: Programming Language :: Python :: 3.6
Classifier: Programming Language :: Python :: 3.7
Classifier: Programming Language :: Python :: Implementation :: CPython
Requires-Python: >=3.6
Provides-Extra: dev
